LICENSE
MANIFEST.in
Makefile
README.rst
ServiceNowRac.spec
dev-requirements.txt
requirements.txt
setup.py
ServiceNowRac/__init__.py
ServiceNowRac/snow_client.py
ServiceNowRac/snow_session.py
ServiceNowRac/snow_table.py
ServiceNowRac.egg-info/PKG-INFO
ServiceNowRac.egg-info/SOURCES.txt
ServiceNowRac.egg-info/dependency_links.txt
ServiceNowRac.egg-info/requires.txt
ServiceNowRac.egg-info/top_level.txt
test/__init__.py
test/fixtures/incident_table.json
test/fixtures/incident_table_delete_multiple.json
test/fixtures/incident_table_delete_record.json
test/fixtures/incident_table_getKeys.json
test/fixtures/incident_table_insert.json
test/fixtures/incident_table_insert_error.json
test/fixtures/incident_table_insert_multiple.json
test/fixtures/incident_table_records.json
test/fixtures/incident_table_sysid.json
test/fixtures/incident_table_update_record.json
test/lib/testlib.py
test/system/__init__.py
test/system/config.py
test/system/test_snow_client.py
test/system/test_snow_table.py
test/unit/__init__.py
test/unit/mock_defs.py
test/unit/test_snow_client.py
test/unit/test_snow_table.py