Metadata-Version: 1.1
Name: ServiceNowRac
Version: 0.5.0
Summary: ServiceNow Rest API Client written in Python
Home-page: https://github.com/aristanetworks/ServiceNowRac/
Author: Arista Networks, Inc.
Author-email: eosplus-dev@arista.com
License: BSD-3
Download-URL: https://github.com/aristanetworks/ServiceNowRac/tarball/0.5.0
Keywords: networking servicenow development rest api
Platform: UNKNOWN
Classifier: Development Status :: 3 - Alpha
Classifier: Intended Audience :: Developers
Classifier: Intended Audience :: System Administrators
Classifier: Topic :: Software Development :: Libraries
Classifier: Topic :: Software Development :: Libraries :: Python Modules
Classifier: Topic :: System :: Networking
Classifier: License :: OSI Approved :: BSD License
Classifier: Programming Language :: Python :: 2
Classifier: Programming Language :: Python :: 2.7
